calculate_mirror_size.py
calculate_mirror_size-0.3.dist-info/METADATA
calculate_mirror_size-0.3.dist-info/WHEEL
calculate_mirror_size-0.3.dist-info/entry_points.txt
calculate_mirror_size-0.3.dist-info/licenses/LICENSE
calculate_mirror_size-0.3.dist-info/RECORD
